snowpack_stack/__init__.py
snowpack_stack/access_control.py
snowpack_stack/auth.py
snowpack_stack/cli/__init__.py
snowpack_stack/cli/auth.py
snowpack_stack/cli/base.py
snowpack_stack/cli/bruin/__init__.py
snowpack_stack/cli/bruin/sql_generator.py
snowpack_stack/cli/bruin/yaml_generator.py
snowpack_stack/cli/build/__init__.py
snowpack_stack/cli/build/all.py
snowpack_stack/cli/build/bruin/__init__.py
snowpack_stack/cli/build/bruin/sql.py
snowpack_stack/cli/build/bruin/yaml.py
snowpack_stack/cli/main.py
snowpack_stack/cli/release/__init__.py
snowpack_stack/cli/release/changelog.py
snowpack_stack/cli/release/check.py
snowpack_stack/cli/release/create.py
snowpack_stack/cli/release/create_command.py
snowpack_stack/cli/release/reset.py
snowpack_stack/cli/release.py
snowpack_stack/cli/setup/__init__.py
snowpack_stack/cli/setup/auth.py
snowpack_stack/cli/setup/rotate_key.py
snowpack_stack/cli/setup/verify.py
snowpack_stack/cli/setup/verify_internal.py
snowpack_stack/cli/tool_manager/__init__.py
snowpack_stack/cli/tool_manager/add_command.py
snowpack_stack/cli/tool_manager/initialize.py
snowpack_stack/cli/tool_manager/install.py
snowpack_stack/cli/tool_manager/metadata.py
snowpack_stack/cli/tool_manager/remove_command.py
snowpack_stack/cli/tool_manager/utils.py
snowpack_stack/cli/tool_manager/verify.py
snowpack_stack/cli/verify.py
snowpack_stack/config_loader.py
snowpack_stack/core/__init__.py
snowpack_stack/core/config.py
snowpack_stack/examples.py
snowpack_stack/generators/__init__.py
snowpack_stack/generators/base.py
snowpack_stack/generators/bruin/__init__.py
snowpack_stack/generators/bruin/sql_generator.py
snowpack_stack/generators/bruin/yaml_generator.py
snowpack_stack/main.py
snowpack_stack/scripts/__init__.py
snowpack_stack/source_handler.py
snowpack_stack/transformer.py
snowpack_stack/type_mapper.py
snowpack_stack/utils/__init__.py
snowpack_stack/utils/db.py
snowpack_stack/utils/logging.py
snowpack_stack/utils/subprocess_utils.py
snowpack_stack/validator.py
snowpack_stack-0.7.8.dist-info/METADATA
snowpack_stack-0.7.8.dist-info/WHEEL
snowpack_stack-0.7.8.dist-info/entry_points.txt
snowpack_stack-0.7.8.dist-info/RECORD
