Metadata-Version: 2.1
Name: snowpack-stack
Version: 0.7.8
Summary: Snowpack Data's internal AI automations for simple, robust, and highly automated Data stack deployments
Home-page: https://snowpack-data.com/
License: MIT
Keywords: data,data engineering,data analytics,pipeline,automation
Author: Snowpack Data
Author-email: company@snowpack-data.io
Requires-Python: >=3.11,<4.0
Classifier: Development Status :: 4 - Beta
Classifier: Intended Audience :: Developers
Classifier: Intended Audience :: Information Technology
Classifier: Intended Audience :: System Administrators
Classifier: License :: OSI Approved :: MIT License
Classifier: Programming Language :: Python :: 3
Classifier: Programming Language :: Python :: 3.11
Classifier: Topic :: Software Development :: Libraries :: Python Modules
Requires-Dist: PyYAML (>=6.0,<7.0)
Requires-Dist: packaging (>=24.0,<25.0)
Requires-Dist: psycopg2-binary (>=2.9,<3.0)
Requires-Dist: python-dotenv (>=1.0,<2.0)
Requires-Dist: pyyaml (>=6.0.1,<7.0.0)
Requires-Dist: requests (>=2.31.0,<3.0.0)
Requires-Dist: tomli (>=2.0.1,<3.0.0)
Requires-Dist: typing-extensions (>=4.9.0,<5.0.0)
Project-URL: Repository, https://github.com/snowpackdata/snowpack_stack/
